Metadata-Version: 2.4
Name: mseep-mcp-registry
Version: 0.1.1
Summary: A registry for MCP servers
Author-email: mseep <support@skydeck.ai>
Requires-Python: <3.13,>=3.12
License-File: LICENSE
Requires-Dist: fastapi>=0.115.12
Requires-Dist: itsdangerous>=2.2.0
Requires-Dist: jinja2>=3.1.6
Requires-Dist: mcp>=1.8.0
Requires-Dist: pydantic>=2.11.3
Requires-Dist: httpx>=0.27.0
Requires-Dist: python-dotenv>=1.1.0
Requires-Dist: python-multipart>=0.0.20
Requires-Dist: uvicorn[standard]>=0.34.2
Requires-Dist: faiss-cpu>=1.7.4
Requires-Dist: sentence-transformers>=2.2.2
Requires-Dist: websockets>=15.0.1
Requires-Dist: scikit-learn>=1.3.0
Requires-Dist: torch>=1.6.0
Requires-Dist: huggingface-hub[cli]>=0.31.1
Requires-Dist: bandit>=1.8.3
Requires-Dist: langchain-mcp-adapters>=0.0.11
Requires-Dist: langgraph>=0.4.3
Requires-Dist: langchain-aws>=0.2.23
Requires-Dist: pytz>=2025.2
Dynamic: license-file
